{
  "_class": "text",
  "attributedString": {
    "_class": "attributedString",
    "attributes": [
      {
        "_class": "stringAttribute",
        "attributes": {
          "MSAttributedStringColorAttribute": {
            "_class": "color",
            "alpha": 1,
            "blue": 0.06666666667,
            "green": 0.06666666667,
            "red": 0.06666666667
          },
          "MSAttributedStringFontAttribute": {
            "_class": "fontDescriptor",
            "attributes": {
              "name": "Lato-Bold",
              "size": 48
            }
          },
          "kerning": 0,
          "paragraphStyle": {
            "_class": "paragraphStyle",
            "allowsDefaultTighteningForTruncation": 0,
            "maximumLineHeight": 56,
            "minimumLineHeight": 56
          }
        },
        "length": 16,
        "location": 0
      }
    ],
    "string": "7:00 PM Tomorrow"
  },
  "automaticallyDrawOnUnderlyingPath": false,
  "booleanOperation": 0,
  "do_objectID": "D1E272A7-703B-4176-92AB-739E714AD2EE",
  "dontSynchroniseWithSymbol": false,
  "exportOptions": {
    "_class": "exportOptions",
    "do_objectID": "B1EF27A8-54A4-43EE-87B6-8ACF7CF36812",
    "exportFormats": [
    ],
    "includedLayerIds": [
    ],
    "layerOptions": 0,
    "shouldTrim": false
  },
  "frame": {
    "_class": "rect",
    "constrainProportions": false,
    "do_objectID": "E77A3946-FB1F-4DB8-AD0F-74F6422A0E7E",
    "height": 56,
    "width": 421,
    "x": 431,
    "y": 72
  },
  "glyphBounds": "{{2, 11}, {418, 37}}",
  "isFixedToViewport": false,
  "isFlippedHorizontal": false,
  "isFlippedVertical": false,
  "isLocked": false,
  "isVisible": true,
  "layerListExpandedType": 0,
  "lineSpacingBehaviour": 2,
  "name": "7:00 PM Tomorrow",
  "nameIsFixed": false,
  "resizingConstraint": 47,
  "resizingType": 0,
  "rotation": 0,
  "shouldBreakMaskChain": false,
  "style": {
    "_class": "style",
    "do_objectID": "F0C3D003-1031-45EC-9FAE-C4B41B01FE28",
    "endMarkerType": 0,
    "miterLimit": 10,
    "sharedObjectID": "8ED1DFDF-DFF2-42D1-BD43-3558439A68F3",
    "startMarkerType": 0,
    "textStyle": {
      "_class": "textStyle",
      "do_objectID": "B9A7CD73-0FFE-4F65-A5BE-D07E1A2A38F6",
      "encodedAttributes": {
        "MSAttributedStringColorAttribute": {
          "_class": "color",
          "alpha": 1,
          "blue": 0.06666666667,
          "green": 0.06666666667,
          "red": 0.06666666667
        },
        "MSAttributedStringFontAttribute": {
          "_class": "fontDescriptor",
          "attributes": {
            "name": "Lato-Bold",
            "size": 48
          }
        },
        "kerning": 0,
        "paragraphStyle": {
          "_class": "paragraphStyle",
          "allowsDefaultTighteningForTruncation": 0,
          "maximumLineHeight": 56,
          "minimumLineHeight": 56
        }
      },
      "verticalAlignment": 0
    },
    "windingRule": 1
  },
  "textBehaviour": 0
}