{
  "_class": "shapeGroup",
  "booleanOperation": 0,
  "clippingMaskMode": 0,
  "do_objectID": "069DF6E2-A675-43A3-9A4D-AE8E9FC5E2D2",
  "exportOptions": {
    "_class": "exportOptions",
    "do_objectID": "372199C2-76D7-4C1A-B542-DF9BCFBD02FB",
    "exportFormats": [
    ],
    "includedLayerIds": [
    ],
    "layerOptions": 0,
    "shouldTrim": false
  },
  "frame": {
    "_class": "rect",
    "constrainProportions": false,
    "do_objectID": "AD692390-6BAC-44B3-BA9F-AC42D4C14059",
    "height": 112,
    "width": 320,
    "x": 0,
    "y": 0
  },
  "hasClickThrough": false,
  "hasClippingMask": false,
  "isFixedToViewport": false,
  "isFlippedHorizontal": false,
  "isFlippedVertical": false,
  "isLocked": false,
  "isVisible": true,
  "layerListExpandedType": 1,
  "layers": [
    {
      "class": "rectangle",
      "id": "68F1C135-7CDC-4577-88D6-F734572E517F"
    }
  ],
  "name": "Button",
  "nameIsFixed": true,
  "resizingConstraint": 63,
  "resizingType": 0,
  "rotation": 0,
  "shouldBreakMaskChain": false,
  "style": {
    "_class": "style",
    "borders": [
      {
        "_class": "border",
        "color": {
          "_class": "color",
          "alpha": 1,
          "blue": 0.592,
          "green": 0.592,
          "red": 0.592
        },
        "fillType": 0,
        "isEnabled": false,
        "position": 1,
        "thickness": 1
      }
    ],
    "do_objectID": "6DE8E9AF-A739-4173-A8FD-4A9E481D5332",
    "endMarkerType": 0,
    "fills": [
      {
        "_class": "fill",
        "color": {
          "_class": "color",
          "alpha": 1,
          "blue": 0.9137254901960784,
          "green": 0.5019607843137255,
          "red": 0.3372549019607843
        },
        "fillType": 0,
        "isEnabled": true,
        "noiseIndex": 0,
        "noiseIntensity": 0,
        "patternFillType": 1,
        "patternTileScale": 1
      }
    ],
    "miterLimit": 10,
    "startMarkerType": 0,
    "windingRule": 1
  },
  "windingRule": 1
}