{
  "_class": "shapePath",
  "booleanOperation": -1,
  "do_objectID": "8CBDC1A0-DD5C-4CE6-93A8-1AE8C3BF124E",
  "edited": true,
  "exportOptions": {
    "_class": "exportOptions",
    "exportFormats": [
    ],
    "includedLayerIds": [
    ],
    "layerOptions": 0,
    "shouldTrim": false
  },
  "frame": {
    "_class": "rect",
    "constrainProportions": false,
    "height": 43,
    "width": 43,
    "x": 0,
    "y": 0
  },
  "isClosed": true,
  "isFlippedHorizontal": false,
  "isFlippedVertical": false,
  "isLocked": false,
  "isVisible": true,
  "layerListExpandedType": 0,
  "name": "Path",
  "nameIsFixed": false,
  "path": {
    "_class": "path",
    "isClosed": true,
    "pointRadiusBehaviour": 1,
    "points": [
      {
        "_class": "curvePoint",
        "cornerRadius": 0,
        "curveFrom": "{1, 0.437500000703125}",
        "curveMode": 1,
        "curveTo": "{1, 0.437500000703125}",
        "hasCurveFrom": false,
        "hasCurveTo": false,
        "point": "{1, 0.437500000703125}"
      },
      {
        "_class": "curvePoint",
        "cornerRadius": 0,
        "curveFrom": "{0.2393750005302735, 0.437500000703125}",
        "curveMode": 1,
        "curveTo": "{0.2393750005302735, 0.437500000703125}",
        "hasCurveFrom": false,
        "hasCurveTo": false,
        "point": "{0.2393750005302735, 0.437500000703125}"
      },
      {
        "_class": "curvePoint",
        "cornerRadius": 0,
        "curveFrom": "{0.58875000091992191, 0.088124999889843736}",
        "curveMode": 1,
        "curveTo": "{0.58875000091992191, 0.088124999889843736}",
        "hasCurveFrom": false,
        "hasCurveTo": false,
        "point": "{0.58875000091992191, 0.088124999889843736}"
      },
      {
        "_class": "curvePoint",
        "cornerRadius": 0,
        "curveFrom": "{0.50000000234375008, 0}",
        "curveMode": 1,
        "curveTo": "{0.50000000234375008, 0}",
        "hasCurveFrom": false,
        "hasCurveTo": false,
        "point": "{0.50000000234375008, 0}"
      },
      {
        "_class": "curvePoint",
        "cornerRadius": 0,
        "curveFrom": "{0, 0.49999999906250003}",
        "curveMode": 1,
        "curveTo": "{0, 0.49999999906250003}",
        "hasCurveFrom": false,
        "hasCurveTo": false,
        "point": "{0, 0.49999999906250003}"
      },
      {
        "_class": "curvePoint",
        "cornerRadius": 0,
        "curveFrom": "{0.50000000234375008, 1}",
        "curveMode": 1,
        "curveTo": "{0.50000000234375008, 1}",
        "hasCurveFrom": false,
        "hasCurveTo": false,
        "point": "{0.50000000234375008, 1}"
      },
      {
        "_class": "curvePoint",
        "cornerRadius": 0,
        "curveFrom": "{0.58812500248144539, 0.91187500011015632}",
        "curveMode": 1,
        "curveTo": "{0.58812500248144539, 0.91187500011015632}",
        "hasCurveFrom": false,
        "hasCurveTo": false,
        "point": "{0.58812500248144539, 0.91187500011015632}"
      },
      {
        "_class": "curvePoint",
        "cornerRadius": 0,
        "curveFrom": "{0.2393750005302735, 0.56249999742187495}",
        "curveMode": 1,
        "curveTo": "{0.2393750005302735, 0.56249999742187495}",
        "hasCurveFrom": false,
        "hasCurveTo": false,
        "point": "{0.2393750005302735, 0.56249999742187495}"
      },
      {
        "_class": "curvePoint",
        "cornerRadius": 0,
        "curveFrom": "{1, 0.56249999742187495}",
        "curveMode": 1,
        "curveTo": "{1, 0.56249999742187495}",
        "hasCurveFrom": false,
        "hasCurveTo": false,
        "point": "{1, 0.56249999742187495}"
      }
    ]
  },
  "pointRadiusBehaviour": 1,
  "points": [
    {
      "_class": "curvePoint",
      "cornerRadius": 0,
      "curveFrom": "{1, 0.437500000703125}",
      "curveMode": 1,
      "curveTo": "{1, 0.437500000703125}",
      "hasCurveFrom": false,
      "hasCurveTo": false,
      "point": "{1, 0.437500000703125}"
    },
    {
      "_class": "curvePoint",
      "cornerRadius": 0,
      "curveFrom": "{0.2393750005302735, 0.437500000703125}",
      "curveMode": 1,
      "curveTo": "{0.2393750005302735, 0.437500000703125}",
      "hasCurveFrom": false,
      "hasCurveTo": false,
      "point": "{0.2393750005302735, 0.437500000703125}"
    },
    {
      "_class": "curvePoint",
      "cornerRadius": 0,
      "curveFrom": "{0.58875000091992191, 0.088124999889843736}",
      "curveMode": 1,
      "curveTo": "{0.58875000091992191, 0.088124999889843736}",
      "hasCurveFrom": false,
      "hasCurveTo": false,
      "point": "{0.58875000091992191, 0.088124999889843736}"
    },
    {
      "_class": "curvePoint",
      "cornerRadius": 0,
      "curveFrom": "{0.50000000234375008, 0}",
      "curveMode": 1,
      "curveTo": "{0.50000000234375008, 0}",
      "hasCurveFrom": false,
      "hasCurveTo": false,
      "point": "{0.50000000234375008, 0}"
    },
    {
      "_class": "curvePoint",
      "cornerRadius": 0,
      "curveFrom": "{0, 0.49999999906250003}",
      "curveMode": 1,
      "curveTo": "{0, 0.49999999906250003}",
      "hasCurveFrom": false,
      "hasCurveTo": false,
      "point": "{0, 0.49999999906250003}"
    },
    {
      "_class": "curvePoint",
      "cornerRadius": 0,
      "curveFrom": "{0.50000000234375008, 1}",
      "curveMode": 1,
      "curveTo": "{0.50000000234375008, 1}",
      "hasCurveFrom": false,
      "hasCurveTo": false,
      "point": "{0.50000000234375008, 1}"
    },
    {
      "_class": "curvePoint",
      "cornerRadius": 0,
      "curveFrom": "{0.58812500248144539, 0.91187500011015632}",
      "curveMode": 1,
      "curveTo": "{0.58812500248144539, 0.91187500011015632}",
      "hasCurveFrom": false,
      "hasCurveTo": false,
      "point": "{0.58812500248144539, 0.91187500011015632}"
    },
    {
      "_class": "curvePoint",
      "cornerRadius": 0,
      "curveFrom": "{0.2393750005302735, 0.56249999742187495}",
      "curveMode": 1,
      "curveTo": "{0.2393750005302735, 0.56249999742187495}",
      "hasCurveFrom": false,
      "hasCurveTo": false,
      "point": "{0.2393750005302735, 0.56249999742187495}"
    },
    {
      "_class": "curvePoint",
      "cornerRadius": 0,
      "curveFrom": "{1, 0.56249999742187495}",
      "curveMode": 1,
      "curveTo": "{1, 0.56249999742187495}",
      "hasCurveFrom": false,
      "hasCurveTo": false,
      "point": "{1, 0.56249999742187495}"
    }
  ],
  "resizingConstraint": 63,
  "resizingType": 0,
  "rotation": 0,
  "shouldBreakMaskChain": false
}