{
  "_class": "shapePath",
  "booleanOperation": -1,
  "do_objectID": "1B47453A-5FFC-4B8A-8891-5452F3F37F14",
  "edited": true,
  "exportOptions": {
    "_class": "exportOptions",
    "do_objectID": "C1F091E3-7D7B-4CFF-915C-DFE060F80643",
    "exportFormats": [
    ],
    "includedLayerIds": [
    ],
    "layerOptions": 0,
    "shouldTrim": false
  },
  "frame": {
    "_class": "rect",
    "constrainProportions": false,
    "do_objectID": "C175DB80-FBBB-46F0-855C-D9E9DCF4C2D6",
    "height": 76.96202531645577,
    "width": 277.8734177215189,
    "x": 0,
    "y": 0
  },
  "isClosed": true,
  "isFixedToViewport": false,
  "isFlippedHorizontal": false,
  "isFlippedVertical": false,
  "isLocked": false,
  "isVisible": true,
  "layerListExpandedType": 0,
  "name": "Path",
  "nameIsFixed": false,
  "pointRadiusBehaviour": 1,
  "points": [
    {
      "_class": "curvePoint",
      "cornerRadius": 0,
      "curveFrom": "{0.96296296296296291, 0}",
      "curveMode": 4,
      "curveTo": "{0.98518518518518505, 0}",
      "hasCurveFrom": false,
      "hasCurveTo": true,
      "point": "{0.96296296296296291, 0}"
    },
    {
      "_class": "curvePoint",
      "cornerRadius": 0,
      "curveFrom": "{0.014814814814814812, 0}",
      "curveMode": 4,
      "curveTo": "{0.037037037037037035, 0}",
      "hasCurveFrom": true,
      "hasCurveTo": false,
      "point": "{0.037037037037037035, 0}"
    },
    {
      "_class": "curvePoint",
      "cornerRadius": 0,
      "curveFrom": "{0, 0.15333333333333335}",
      "curveMode": 4,
      "curveTo": "{0, 0.073333333333333389}",
      "hasCurveFrom": false,
      "hasCurveTo": true,
      "point": "{0, 0.15333333333333335}"
    },
    {
      "_class": "curvePoint",
      "cornerRadius": 0,
      "curveFrom": "{0, 1}",
      "curveMode": 1,
      "curveTo": "{0, 1}",
      "hasCurveFrom": false,
      "hasCurveTo": false,
      "point": "{0, 1}"
    },
    {
      "_class": "curvePoint",
      "cornerRadius": 0,
      "curveFrom": "{1, 1}",
      "curveMode": 1,
      "curveTo": "{1, 1}",
      "hasCurveFrom": false,
      "hasCurveTo": false,
      "point": "{1, 1}"
    },
    {
      "_class": "curvePoint",
      "cornerRadius": 0,
      "curveFrom": "{1, 0.073333333333333389}",
      "curveMode": 4,
      "curveTo": "{1, 0.15333333333333335}",
      "hasCurveFrom": true,
      "hasCurveTo": false,
      "point": "{1, 0.15333333333333335}"
    }
  ],
  "resizingConstraint": 63,
  "resizingType": 0,
  "rotation": 0,
  "shouldBreakMaskChain": false
}